simple_mqtt-0.1.2.dist-info/licenses/LICENSE
simplemqtt/__init__.py
simplemqtt/mqtt_config.py
simplemqtt/mqtt_message.py
simplemqtt/py.typed
simplemqtt/setup_logging.py
simplemqtt/mqtt_builder/__init__.py
simplemqtt/mqtt_builder/mqtt_builder_base.py
simplemqtt/mqtt_builder/mqtt_builder_v3.py
simplemqtt/mqtt_builder/mqtt_builder_v5.py
simplemqtt/mqtt_connections/__init__.py
simplemqtt/mqtt_connections/mqtt_connection_base.py
simplemqtt/mqtt_connections/mqtt_connection_v3.py
simplemqtt/mqtt_connections/mqtt_connection_v5.py
simplemqtt/types/__init__.py
simplemqtt/types/quality_of_service.py
simplemqtt/types/retain_handling.py
simple_mqtt-0.1.2.dist-info/METADATA
simple_mqtt-0.1.2.dist-info/WHEEL
simple_mqtt-0.1.2.dist-info/top_level.txt
simple_mqtt-0.1.2.dist-info/RECORD
