Metadata-Version: 2.4
Name: simple-mqtt
Version: 0.1.2
Summary: Framework for building easy MQTT applications
Author: Dev-CorliJoni
License-Expression: MIT
Project-URL: GitHub, https://github.com/Dev-CorliJoni/simple-mqtt
Project-URL: Source, https://github.com/Dev-CorliJoni/simple-mqtt
Project-URL: Issues, https://github.com/Dev-CorliJoni/simple-mqtt/issues
Project-URL: Instagram, https://www.instagram.com/dev.corlijoni/
Keywords: mqtt,iot
Classifier: Development Status :: 4 - Beta
Classifier: Intended Audience :: Developers
Classifier: Programming Language :: Python :: 3
Classifier: Programming Language :: Python :: 3.8
Classifier: Programming Language :: Python :: 3.9
Classifier: Programming Language :: Python :: 3.10
Classifier: Programming Language :: Python :: 3.11
Classifier: Programming Language :: Python :: 3.12
Classifier: Operating System :: OS Independent
Classifier: Topic :: Internet
Classifier: Topic :: Software Development :: Libraries :: Python Modules
Requires-Python: >=3.8
License-File: LICENSE
Requires-Dist: paho-mqtt<3,>=1.6
Dynamic: license-file
